pityutest/__init__.py
pityutest/main.py
pityutest-1.4.dist-info/METADATA
pityutest-1.4.dist-info/WHEEL
pityutest-1.4.dist-info/top_level.txt
pityutest-1.4.dist-info/RECORD
