Metadata-Version: 2.1
Name: pityutest
Version: 1.4
Summary: A description of your package
Home-page: https://github.com/pista1125/pityutest
Author: Pityu
Author-email: pista1125@gmail.com
License: MIT
